odoo/addons/account_financial_report_date_range/README.rst
odoo/addons/account_financial_report_date_range/__init__.py
odoo/addons/account_financial_report_date_range/__manifest__.py
odoo/addons/account_financial_report_date_range/i18n/account_financial_report_date_range.pot
odoo/addons/account_financial_report_date_range/i18n/de.po
odoo/addons/account_financial_report_date_range/i18n/it.po
odoo/addons/account_financial_report_date_range/readme/CONTRIBUTORS.rst
odoo/addons/account_financial_report_date_range/readme/DESCRIPTION.rst
odoo/addons/account_financial_report_date_range/readme/INSTALL.rst
odoo/addons/account_financial_report_date_range/static/description/icon.png
odoo/addons/account_financial_report_date_range/static/description/index.html
odoo/addons/account_financial_report_date_range/tests/__init__.py
odoo/addons/account_financial_report_date_range/tests/test_accounting_report.py
odoo/addons/account_financial_report_date_range/wizards/__init__.py
odoo/addons/account_financial_report_date_range/wizards/account_common_report.py
odoo/addons/account_financial_report_date_range/wizards/accounting_report.xml
odoo11_addon_account_financial_report_date_range-11.0.1.0.0.99.dev7.dist-info/METADATA
odoo11_addon_account_financial_report_date_range-11.0.1.0.0.99.dev7.dist-info/WHEEL
odoo11_addon_account_financial_report_date_range-11.0.1.0.0.99.dev7.dist-info/top_level.txt
odoo11_addon_account_financial_report_date_range-11.0.1.0.0.99.dev7.dist-info/RECORD
